ecs_logger/__init__.py
ecs_logger/ecs_meta.py
ecs_logger/logger.py
ecs_logger/logging.py
ecs_logger-0.0.7.dist-info/METADATA
ecs_logger-0.0.7.dist-info/WHEEL
ecs_logger-0.0.7.dist-info/top_level.txt
ecs_logger-0.0.7.dist-info/RECORD
