Metadata-Version: 2.1
Name: ecs-logger
Version: 0.0.7
Summary: ECS Logger
Home-page: https://github.com/hampsterx/ecs-logger
Author: Tim van der Hulst
Author-email: tim.vdh@gmail.com
License: Apache2
Platform: UNKNOWN
Classifier: Development Status :: 4 - Beta
Classifier: Intended Audience :: System Administrators
Classifier: License :: OSI Approved :: Apache Software License
Classifier: Programming Language :: Python :: 3
Requires-Dist: requests (>=2)
Requires-Dist: coloredlogs (==10.0)
Requires-Dist: logaugment (==0.1.3)
Requires-Dist: rfc3339 (==6.0)
